{"generated_at": "2026-07-07T04:39:32+00:00", "series": {"price_day_ahead": {"status": "ok", "last_value_at": "2026-07-07T21:00:00+00:00", "age_hours": -16.3, "rows": 48263}, "load": {"status": "ok", "last_value_at": "2026-07-07T03:00:00+00:00", "age_hours": 1.7, "rows": 48245}, "residual_load": {"status": "ok", "last_value_at": "2026-07-07T03:00:00+00:00", "age_hours": 1.7, "rows": 48245}, "forecast_generation_total": {"status": "ok", "last_value_at": "2026-07-07T21:00:00+00:00", "age_hours": -16.3, "rows": 48263}, "forecast_wind_onshore": {"status": "ok", "last_value_at": "2026-07-07T21:00:00+00:00", "age_hours": -16.3, "rows": 48263}, "forecast_wind_offshore": {"status": "ok", "last_value_at": "2026-07-07T21:00:00+00:00", "age_hours": -16.3, "rows": 48263}, "forecast_solar": {"status": "ok", "last_value_at": "2026-07-07T21:00:00+00:00", "age_hours": -16.3, "rows": 48263}, "gen_lignite": {"status": "ok", "last_value_at": "2026-07-07T03:00:00+00:00", "age_hours": 1.7, "rows": 21869}, "gen_nuclear": {"status": "stale", "last_value_at": "2024-01-30T10:00:00+00:00", "age_hours": 21330.7, "rows": 540}, "gen_wind_offshore": {"status": "ok", "last_value_at": "2026-07-07T03:00:00+00:00", "age_hours": 1.7, "rows": 21869}, "gen_hydro": {"status": "ok", "last_value_at": "2026-07-07T03:00:00+00:00", "age_hours": 1.7, "rows": 21869}, "gen_other_conventional": {"status": "ok", "last_value_at": "2026-07-07T03:00:00+00:00", "age_hours": 1.7, "rows": 21869}, "gen_other_renewable": {"status": "ok", "last_value_at": "2026-07-07T03:00:00+00:00", "age_hours": 1.7, "rows": 21869}, "gen_biomass": {"status": "ok", "last_value_at": "2026-07-07T03:00:00+00:00", "age_hours": 1.7, "rows": 21869}, "gen_wind_onshore": {"status": "ok", "last_value_at": "2026-07-07T03:00:00+00:00", "age_hours": 1.7, "rows": 21869}, "gen_solar": {"status": "ok", "last_value_at": "2026-07-07T03:00:00+00:00", "age_hours": 1.7, "rows": 21869}, "gen_hard_coal": {"status": "ok", "last_value_at": "2026-07-07T03:00:00+00:00", "age_hours": 1.7, "rows": 21869}, "gen_pumped_storage": {"status": "ok", "last_value_at": "2026-07-07T03:00:00+00:00", "age_hours": 1.7, "rows": 21869}, "gen_gas": {"status": "ok", "last_value_at": "2026-07-07T03:00:00+00:00", "age_hours": 1.7, "rows": 21869}}}
